LICENSE
MANIFEST.in
README.md
Readme.md
setup.cfg
setup.py
egeaML/__init__.py
egeaML/constants.py
egeaML/dataingestion.py
egeaML/egeaML.py
egeaML/preprocessing.py
egeaML.egg-info/PKG-INFO
egeaML.egg-info/SOURCES.txt
egeaML.egg-info/dependency_links.txt
egeaML.egg-info/requires.txt
egeaML.egg-info/top_level.txt
tests/__init__.py
tests/data_ingestion/__init__.py
tests/data_ingestion/fixture.py
tests/data_ingestion/test_base.py
tests/preprocessing/__init__.py
tests/preprocessing/test_imputation.py