Metadata-Version: 2.1
Name: egeaML
Version: 1.0.2
Summary: A python library used in support of the Book'Applied Machine Learning with Python'
Home-page: https://github.com/andreagiussani/Applied_Machine_Learning_with_Python
Author: Andrea Giussani
Author-email: andrea.giussani@unibocconi.it
License: BSD
License-File: LICENSE
